logkiss-2.3.3.dist-info/METADATA
logkiss-2.3.3.dist-info/WHEEL
logkiss-2.3.3.dist-info/entry_points.txt
logkiss-2.3.3.dist-info/licenses/LICENSE
logkiss/__init__.py
logkiss/config.py
logkiss/handler_aws.py
logkiss/handler_gcp.py
logkiss/handler_qt.py
logkiss/handlers.py
logkiss/logkiss.py
logkiss-2.3.3.dist-info/RECORD
