Metadata-Version: 2.1
Name: logkiss
Version: 2.3.3
Summary: A simple, colorful, and drop-in replacement for Python's standard logging module. 彩色ログ・彩色日志・カラー対応・颜色日志・多言語対応のシンプルなPythonログライブラリ。Supports colorful/colourful/カラー/彩色/颜色 log output for Python logging, ログ, 日志, ロギング, logger, logging, simple, easy.
Keywords: logging,color,colour,colorful,colourful,console,terminal,logger,python,simple,easy,カラー,コンソール,彩色日志,色付き,ログ,ロギング,ログ出力,日志,颜色,日志输出
Author-Email: Taka Suzuki <tkykszk@gmail.com>
License: MIT
Classifier: Development Status :: 4 - Beta
Classifier: Intended Audience :: Developers
Classifier: License :: OSI Approved :: MIT License
Classifier: Programming Language :: Python :: 3
Classifier: Programming Language :: Python :: 3.7
Classifier: Programming Language :: Python :: 3.8
Classifier: Programming Language :: Python :: 3.9
Classifier: Programming Language :: Python :: 3.10
Classifier: Programming Language :: Python :: 3.11
Classifier: Programming Language :: Python :: 3.12
Classifier: Programming Language :: Python :: 3.13
Classifier: Programming Language :: Python :: 3.14
Classifier: Topic :: Software Development :: Libraries :: Python Modules
Classifier: Topic :: System :: Logging
Project-URL: Homepage, https://github.com/tkykszk/logkiss
Project-URL: Repository, https://github.com/tkykszk/logkiss
Project-URL: Documentation, https://github.com/tkykszk/logkiss/blob/main/README.md
Requires-Python: >=3.7
Requires-Dist: pyyaml>=6.0
Provides-Extra: test
Requires-Dist: pytest>=7.0.0; extra == "test"
Requires-Dist: matplotlib>=3.7.0; extra == "test"
Requires-Dist: logging_tree>=1.9; extra == "test"
Requires-Dist: boto3>=1.34.0; extra == "test"
Requires-Dist: google-cloud-logging>=3.9.0; extra == "test"
Provides-Extra: cloud
Requires-Dist: google-cloud-logging>=3.9.0; extra == "cloud"
Requires-Dist: boto3>=1.34.0; extra == "cloud"
